cellanova/__init__.py
cellanova/model.py
cellanova/utils.py
cellanova-0.1.0.dist-info/LICENSE
cellanova-0.1.0.dist-info/METADATA
cellanova-0.1.0.dist-info/WHEEL
cellanova-0.1.0.dist-info/top_level.txt
cellanova-0.1.0.dist-info/RECORD
