Metadata-Version: 2.1
Name: cellanova
Version: 0.1.0
Summary: Cell state space analysis of variance for signal recovery with batch correction 
Author: Zongming Ma, Nancy Zhang
Author-email: Jane Zhang <zjzhang1235@gmail.com>
Project-URL: Homepage, https://github.com/Janezjz/cellanova
Classifier: Programming Language :: Python :: 3
Classifier: Operating System :: OS Independent
Requires-Python: >=3.7
License-File: LICENSE
Requires-Dist: numpy (>=1.20.3)
Requires-Dist: matplotlib
Requires-Dist: seaborn
Requires-Dist: scanpy (>=1.8.1)
Requires-Dist: statsmodels (>=0.12.2)
Requires-Dist: anndata (>=0.7.6)
Requires-Dist: pandas (>=1.1.0)
Requires-Dist: scipy (>=1.7.1)
Requires-Dist: scikit-learn (>=1.0.2)
Requires-Dist: harmonypy (>=0.0.6)
